{
  "project_info": {
    "project_number": "561068415236",
    "firebase_url": "https://iot-firebase-cc75c-default-rtdb.firebaseio.com",
    "project_id": "iot-firebase-cc75c",
    "storage_bucket": "iot-firebase-cc75c.appspot.com"
  },
  "client": [
    {
      "client_info": {
        "mobilesdk_app_id": "1:561068415236:android:3012ada84f3efd008d1851",
        "android_client_info": {
          "package_name": "com.example.iot_firebase"
        }
      },
      "oauth_client": [],
      "api_key": [
        {
          "current_key": "AIzaSyAdFmIDjCMSW7H61BW1eDas_yLGTf54M1k"
        }
      ],
      "services": {
        "appinvite_service": {
          "other_platform_oauth_client": []
        }
      }
    }
  ],
  "configuration_version": "1"
}